setup.cfg
setup.py
heywatch/__init__.py
heywatch/config.py
heywatch/job.py
heywatch.egg-info/PKG-INFO
heywatch.egg-info/SOURCES.txt
heywatch.egg-info/dependency_links.txt
heywatch.egg-info/requires.txt
heywatch.egg-info/top_level.txt