Metadata-Version: 1.0
Name: heywatch
Version: 2.2.1
Summary: A python wrapper around the HeyWatch API
Home-page: http://www.heywatchencoding.com
Author: Bruno Celeste
Author-email: bruno@heywatch.com
License: MIT License
Keywords: heywatch api
Platform: UNKNOWN
